ulib/VERSION.txt
ulib/__init__.py
ulib/talib.py
ulib/functions/__init__.py
ulib/functions/cycle_indicators.py
ulib/functions/math_operators.py
ulib/functions/math_transform.py
ulib/functions/momentum_indicator.py
ulib/functions/overlap_studies.py
ulib/functions/pattern_recognition.py
ulib/functions/price_transform.py
ulib/functions/statistic_functions.py
ulib/functions/volatility_indicators.py
ulib/functions/volume_indicators.py
ulib/tdx/__init__.py
ulib/tdx/expression_functions.py
ulib-1.0.4.dist-info/DESCRIPTION.rst
ulib-1.0.4.dist-info/METADATA
ulib-1.0.4.dist-info/RECORD
ulib-1.0.4.dist-info/WHEEL
ulib-1.0.4.dist-info/metadata.json
ulib-1.0.4.dist-info/top_level.txt
